{"m":{"v":2,"c":"shopping","n":68},"e":[{"i":"mul-thing","k":"물건","r":"mulgeon","t":{"w":"thing / item / goods","x":"Something you can touch with hands. Products.","e":["I buy thing / item / goods.","thing / item / goods is on sale.","When buying thing / item / goods, you should check the quality.","Understanding thing / item / goods market trends enables smart consumption."]},"g":["shopping","item","basic"],"p":["[물건]","[mulɡʌn]"],"h":1},{"i":"gagyeok","k":"가격","r":"gagyeok","t":{"w":"price","x":"The amount of money when buying and selling things.","e":["I buy price.","price is on sale.","When buying price, you should check the quality.","Understanding price market trends enables smart consumption."]},"g":["shopping","price","basic"],"p":["[가격]","[kaɡjʌk]"],"h":1},{"i":"bissada","k":"비싸다","r":"bissada","t":{"w":"expensive","x":"The price is high.","e":["I buy expensive.","expensive is on sale.","When buying expensive, you should check the quality.","Understanding expensive market trends enables smart consumption."]},"s":2,"g":["shopping","price","expensive"],"p":["[비싸다]","[pisːada]"],"h":1},{"i":"ssada","k":"싸다","r":"ssada","t":{"w":"cheap / inexpensive","x":"The price is low.","e":["I buy cheap / inexpensive.","cheap / inexpensive is on sale.","When buying cheap / inexpensive, you should check the quality.","Understanding cheap / inexpensive market trends enables smart consumption."]},"s":2,"g":["shopping","price","cheap"],"p":["[싸다]","[sːada]"],"h":1},{"i":"halinhada","k":"할인","r":"halin","t":{"w":"discount","x":"Lowering the price.","e":["I buy discount.","discount is on sale.","When buying discount, you should check the quality.","Understanding discount market trends enables smart consumption."]},"g":["shopping","discount","basic"],"p":["[할인하다]","[haɾinɦada]"],"h":1},{"i":"gyesan","k":"계산","r":"gyesan","t":{"w":"payment / calculation","x":"Paying for goods. Or counting numbers.","e":["I buy payment / calculation.","payment / calculation is on sale.","When buying payment / calculation, you should check the quality.","Understanding payment / calculation market trends enables smart consumption."]},"g":["shopping","payment","basic"],"p":["[계산]","[kjesan]"],"h":1},{"i":"yeongsujeung","k":"영수증","r":"yeongsujeung","t":{"w":"receipt","x":"Paper received as proof of purchase.","e":["I buy receipt.","receipt is on sale.","When buying receipt, you should check the quality.","Understanding receipt market trends enables smart consumption."]},"g":["shopping","receipt","basic"],"p":["[영수증]","[jʌŋsudʑɯŋ]"],"h":1},{"i":"hyeongeum","k":"현금","r":"hyeongeum","t":{"w":"cash","x":"Bills and coins. Money that is not card.","e":["I buy cash.","cash is on sale.","When buying cash, you should check the quality.","Understanding cash market trends enables smart consumption."]},"g":["shopping","payment","cash"],"p":["[현금]","[hjʌŋɡɯm]"],"h":1},{"i":"kadeu","k":"카드","r":"kadeu","t":{"w":"card","x":"Credit card or debit card.","e":["I buy card.","card is on sale.","When buying card, you should check the quality.","Understanding card market trends enables smart consumption."]},"g":["shopping","payment","card"],"p":["[카드]","[kʰadɯ]"],"h":1},{"i":"geosileum","k":"거스름돈","r":"geoseureumdon","t":{"w":"change (money)","x":"Money left over after paying for goods.","e":["I buy change (money).","change (money) is on sale.","When buying change (money), you should check the quality.","Understanding change (money) market trends enables smart consumption."]},"d":1,"g":["shopping","payment","change"],"p":["[거스름돈]","[kʌsɯɾɯmton]"],"f":1,"h":1},{"i":"sangjeom","k":"상점","r":"sangjeom","t":{"w":"store / shop","x":"A place that sells goods.","e":["I buy store / shop.","store / shop is on sale.","When buying store / shop, you should check the quality.","Understanding store / shop market trends enables smart consumption."]},"g":["shopping","store","basic"],"p":["[상점]","[saŋdʑʌm]"],"h":1},{"i":"mawet","k":"마트","r":"mateu","t":{"w":"mart / supermarket","x":"A large store selling daily necessities and food.","e":["I buy mart / supermarket.","mart / supermarket is on sale.","When buying mart / supermarket, you should check the quality.","Understanding mart / supermarket market trends enables smart consumption."]},"g":["shopping","supermarket","basic"],"p":["[마트]","[matʰɯ]"],"h":1},{"i":"baekwajeom","k":"백화점","r":"baekwajeom","t":{"w":"department store","x":"A large building selling various kinds of goods.","e":["I buy department store.","department store is on sale.","When buying department store, you should check the quality.","Understanding department store market trends enables smart consumption."]},"g":["shopping","department store","basic"],"p":["[백화점]","[pɛkʰwadʑʌm]"],"h":1},{"i":"pyeoneuijeom","k":"편의점","r":"pyeonuijeom","t":{"w":"convenience store","x":"A small store operating 24 hours.","e":["I buy convenience store.","convenience store is on sale.","When buying convenience store, you should check the quality.","Understanding convenience store market trends enables smart consumption."]},"g":["shopping","convenience store","basic"],"p":["[편의점]","[pʰjʌnɯidʑʌm]"],"h":1},{"i":"sijang","k":"시장","r":"sijang","t":{"w":"market","x":"A place where many stores gather to sell goods.","e":["I buy market.","market is on sale.","When buying market, you should check the quality.","Understanding market market trends enables smart consumption."]},"g":["shopping","market","basic"],"p":["[시장]","[ɕidʑaŋ]"],"h":1},{"i":"onlain","k":"온라인","r":"onlain","t":{"w":"online","x":"Through the internet.","e":["I buy online.","online is on sale.","When buying online, you should check the quality.","Understanding online market trends enables smart consumption."]},"g":["shopping","online","modern"],"p":["[온라인]","[onɾain]"],"h":1},{"i":"baedal","k":"배달","r":"baedal","t":{"w":"delivery","x":"Bringing goods or food.","e":["I buy delivery.","delivery is on sale.","When buying delivery, you should check the quality.","Understanding delivery market trends enables smart consumption."]},"g":["shopping","delivery","basic"],"p":["[배달]","[pɛdal]"],"h":1},{"i":"jumun","k":"주문","r":"jumun","t":{"w":"order","x":"Requesting to buy goods or food.","e":["I buy order.","order is on sale.","When buying order, you should check the quality.","Understanding order market trends enables smart consumption."]},"g":["shopping","order","basic"],"p":["[주문]","[tɕumun]"],"h":1},{"i":"hwanbul","k":"환불","r":"hwanbul","t":{"w":"refund","x":"Returning purchased goods and getting money back.","e":["I buy refund.","refund is on sale.","When buying refund, you should check the quality.","Understanding refund market trends enables smart consumption."]},"d":1,"g":["shopping","refund","return"],"p":["[환불]","[hwanbul]"],"f":1,"h":1},{"i":"gyohwan","k":"교환","r":"gyohwan","t":{"w":"exchange","x":"Changing purchased goods for something else.","e":["I buy exchange.","exchange is on sale.","When buying exchange, you should check the quality.","Understanding exchange market trends enables smart consumption."]},"d":1,"g":["shopping","exchange","return"],"p":["[교환]","[kjoɦwan]"],"f":1,"h":1},{"i":"saizeu","k":"사이즈","r":"saijeu","t":{"w":"size","x":"The size of clothes or shoes.","e":["I buy size.","size is on sale.","When buying size, you should check the quality.","Understanding size market trends enables smart consumption."]},"g":["shopping","size","clothing"],"p":["[사이즈]","[saidzɯ]"],"h":1},{"i":"saek-shopping","k":"색","r":"saek","t":{"w":"color","x":"Hues like red, blue, etc.","e":["I buy color.","color is on sale.","When buying color, you should check the quality.","Understanding color market trends enables smart consumption."]},"g":["shopping","color","basic"],"p":["[색]","[sɛk]"],"h":1},{"i":"ibeo","k":"입어 보다","r":"ibeo boda","t":{"w":"to try on","x":"To wear clothes to check before buying.","e":["I buy to try on.","to try on is on sale.","When buying to try on, you should check the quality.","Understanding to try on market trends enables smart consumption."]},"s":1,"g":["shopping","trying on","clothing"],"p":["[입어보다]","[ibʌboda]"],"h":1},{"i":"talleusil","k":"탈의실","r":"tareuisil","t":{"w":"fitting room / changing room","x":"A room for changing clothes.","e":["I buy fitting room / changing room.","fitting room / changing room is on sale.","When buying fitting room / changing room, you should check the quality.","Understanding fitting room / changing room market trends enables smart consumption."]},"d":1,"g":["shopping","fitting room","clothing"],"p":["[탈의실]","[tʰaɾɯiɕil]"],"f":1,"h":1},{"i":"jangbagu","k":"장바구니","r":"jangbaguni","t":{"w":"shopping cart / basket","x":"A basket for putting items when shopping. Online, it's the list of items to buy.","e":["I buy shopping cart / basket.","shopping cart / basket is on sale.","When buying shopping cart / basket, you should check the quality.","Understanding shopping cart / basket market trends enables smart consumption."]},"g":["shopping","cart","basic"],"p":["[장바구니]","[tɕaŋbaɡuni]"],"h":1},{"i":"pojang","k":"포장","r":"pojang","t":{"w":"wrapping / packaging","x":"Wrapping or decorating items.","e":["I buy wrapping / packaging.","wrapping / packaging is on sale.","When buying wrapping / packaging, you should check the quality.","Understanding wrapping / packaging market trends enables smart consumption."]},"g":["shopping","wrapping","gift"],"p":["[포장]","[pʰodʑaŋ]"],"h":1},{"i":"seonmul","k":"선물","r":"seonmul","t":{"w":"gift / present","x":"An item given to another person.","e":["I buy gift / present.","gift / present is on sale.","When buying gift / present, you should check the quality.","Understanding gift / present market trends enables smart consumption."]},"g":["shopping","gift","basic"],"p":["[선물]","[sʌnmul]"],"h":1},{"i":"sangpum","k":"상품","r":"sangpum","t":{"w":"product / goods","x":"Items made for selling.","e":["I buy product / goods.","product / goods is on sale.","When buying product / goods, you should check the quality.","Understanding product / goods market trends enables smart consumption."]},"g":["shopping","product","basic"],"p":["[상품]","[saŋpʰum]"],"h":1},{"i":"jeungum","k":"품질","r":"pumjil","t":{"w":"quality","x":"The degree of how good an item is.","e":["I buy quality.","quality is on sale.","When buying quality, you should check the quality.","Understanding quality market trends enables smart consumption."]},"d":1,"g":["shopping","quality","evaluation"],"p":["[정품]","[tɕʌŋpʰum]"],"f":1,"h":1},{"i":"gokaek","k":"고객","r":"gogaek","t":{"w":"customer / client","x":"A person who buys goods. A guest.","e":["I buy customer / client.","customer / client is on sale.","When buying customer / client, you should check the quality.","Understanding customer / client market trends enables smart consumption."]},"d":1,"g":["shopping","customer","service"],"p":["[고객]","[koɡɛk]"],"f":1,"h":1},{"i":"jeongweon","k":"점원","r":"jeomwon","t":{"w":"store clerk / salesperson","x":"A person who works at a store.","e":["I buy store clerk / salesperson.","store clerk / salesperson is on sale.","When buying store clerk / salesperson, you should check the quality.","Understanding store clerk / salesperson market trends enables smart consumption."]},"g":["shopping","staff","service"],"p":["[점원]","[tɕʌmwʌn]"],"h":1},{"i":"seobiseu","k":"서비스","r":"seobiseu","t":{"w":"service / free item","x":"Help for customers. Or something given for free.","e":["I buy service / free item.","service / free item is on sale.","When buying service / free item, you should check the quality.","Understanding service / free item market trends enables smart consumption."]},"g":["shopping","service","free"],"p":["[서비스]","[sʌbisɯ]"],"h":1},{"i":"seil","k":"세일","r":"seil","t":{"w":"sale","x":"Selling goods at a discount.","e":["I buy sale.","sale is on sale.","When buying sale, you should check the quality.","Understanding sale market trends enables smart consumption."]},"g":["shopping","sale","discount"],"p":["[세일]","[seil]"],"h":1},{"i":"inggi","k":"인기","r":"ingi","t":{"w":"popularity","x":"Something that many people like and are interested in.","e":["I buy popularity.","popularity is on sale.","When buying popularity, you should check the quality.","Understanding popularity market trends enables smart consumption."]},"g":["shopping","popularity","trend"],"p":["[인기]","[iŋɡi]"],"h":1},{"i":"brandu","k":"브랜드","r":"beulaendeu","t":{"w":"brand","x":"The name of a company that makes products.","e":["I buy brand.","brand is on sale.","When buying brand, you should check the quality.","Understanding brand market trends enables smart consumption."]},"g":["shopping","brand","modern"],"p":["[브랜드]","[pɯɾɛndɯ]"],"h":1},{"i":"maejin","k":"품절","r":"pumjeol","t":{"w":"sold out","x":"Items are all sold and none left.","e":["I buy sold out.","sold out is on sale.","When buying sold out, you should check the quality.","Understanding sold out market trends enables smart consumption."]},"d":1,"g":["shopping","sold out","stock"],"p":["[매진]","[mɛdʑin]"],"f":1,"h":1},{"i":"jaego","k":"재고","r":"jaego","t":{"w":"stock / inventory","x":"Items that remain unsold.","e":["I buy stock / inventory.","stock / inventory is on sale.","When buying stock / inventory, you should check the quality.","Understanding stock / inventory market trends enables smart consumption."]},"d":1,"g":["shopping","stock","inventory"],"p":["[재고]","[tɕɛɡo]"],"f":1,"h":1},{"i":"mulgap","k":"물가","r":"mulga","t":{"w":"prices (general) / cost of living","x":"The general price level of goods.","e":["I buy prices (general) / cost of living.","prices (general) / cost of living is on sale.","When buying prices (general) / cost of living, you should check the quality.","Understanding prices (general) / cost of living market trends enables smart consumption."]},"d":1,"g":["shopping","prices","economy"],"p":["[물가]","[mulɡa]"],"f":1,"h":1},{"i":"guipun","k":"쿠폰","r":"kupon","t":{"w":"coupon","x":"Paper or code to receive discounts or services.","e":["I buy coupon.","coupon is on sale.","When buying coupon, you should check the quality.","Understanding coupon market trends enables smart consumption."]},"g":["shopping","coupon","discount"],"p":["[쿠폰]","[kʰupʰon]"],"h":1},{"i":"poinneu","k":"포인트","r":"pointeu","t":{"w":"points","x":"Points accumulated when purchasing. Can be used like cash later.","e":["I buy points.","points is on sale.","When buying points, you should check the quality.","Understanding points market trends enables smart consumption."]},"g":["shopping","points","reward"],"p":["[포인트]","[pʰointʰɯ]"],"h":1},{"i":"meombuseup","k":"멤버십","r":"membeosip","t":{"w":"membership","x":"Becoming a member of a specific group. Can receive special benefits.","e":["I buy membership.","membership is on sale.","When buying membership, you should check the quality.","Understanding membership market trends enables smart consumption."]},"d":1,"g":["shopping","membership","loyalty"],"p":["[멤버십]","[membʌɕip]"],"f":1,"h":1},{"i":"bidgyo","k":"비교","r":"bigyo","t":{"w":"comparison","x":"Looking at two or more things together.","e":["I buy comparison.","comparison is on sale.","When buying comparison, you should check the quality.","Understanding comparison market trends enables smart consumption."]},"d":1,"g":["shopping","comparison","decision"],"p":["[비교]","[piɡjo]"],"f":1,"h":1},{"i":"hugi","k":"후기","r":"hugi","t":{"w":"review","x":"Evaluation or opinion after using a product.","e":["I buy review.","review is on sale.","When buying review, you should check the quality.","Understanding review market trends enables smart consumption."]},"d":1,"g":["shopping","review","feedback"],"p":["[후기]","[huɡi]"],"f":1,"h":1},{"i":"byeoljeom","k":"별점","r":"byeoljeom","t":{"w":"star rating","x":"Rating score displayed by number of stars.","e":["I buy star rating.","star rating is on sale.","When buying star rating, you should check the quality.","Understanding star rating market trends enables smart consumption."]},"d":1,"g":["shopping","rating","feedback"],"p":["[별점]","[pjʌldʑʌm]"],"f":1,"h":1},{"i":"chungdong","k":"충동구매","r":"chungdonggumae","t":{"w":"impulse buying","x":"Buying suddenly without planning.","e":["I buy impulse buying.","impulse buying is on sale.","When buying impulse buying, you should check the quality.","Understanding impulse buying market trends enables smart consumption."]},"d":1,"g":["shopping","impulse","behavior"],"p":["[충동]","[tɕʰuŋdoŋ]"],"f":1,"h":1},{"i":"jeoryak","k":"절약","r":"jeoryak","t":{"w":"saving / economizing","x":"Using money or resources sparingly.","e":["I buy saving / economizing.","saving / economizing is on sale.","When buying saving / economizing, you should check the quality.","Understanding saving / economizing market trends enables smart consumption."]},"d":1,"g":["shopping","saving","money"],"p":["[저렴]","[tɕʌɾjʌm]"],"f":1,"h":1},{"i":"maejang","k":"매장","r":"maejang","t":{"w":"store / shop","x":"A store or shop that sells items.","e":["I buy store / shop.","store / shop is on sale.","When buying store / shop, you should check the quality.","Understanding store / shop market trends enables smart consumption."]},"g":["shopping","store","place"],"p":["[매장]","[mɛdʑaŋ]"],"h":1},{"i":"haengsabum","k":"행사품","r":"haengsabum","t":{"w":"sale item / promotional product","x":"Products discounted through sales or events.","e":["I buy sale item / promotional product.","sale item / promotional product is on sale.","When buying sale item / promotional product, you should check the quality.","Understanding sale item / promotional product market trends enables smart consumption."]},"d":1,"g":["shopping","sale","promotion"],"p":["[행사품]","[hɛŋsapʰum]"],"f":1,"h":1},{"i":"jeongga","k":"정가","r":"jeongga","t":{"w":"regular price / list price","x":"The set original price.","e":["I buy regular price / list price.","regular price / list price is on sale.","When buying regular price / list price, you should check the quality.","Understanding regular price / list price market trends enables smart consumption."]},"d":1,"g":["shopping","price","original"],"p":["[정가]","[tɕʌŋɡa]"],"f":1,"h":1},{"i":"pyosigage","k":"표시 가격","r":"pyosi gagyek","t":{"w":"displayed price / marked price","x":"The price shown on a product.","e":["I buy displayed price / marked price.","displayed price / marked price is on sale.","When buying displayed price / marked price, you should check the quality.","Understanding displayed price / marked price market trends enables smart consumption."]},"d":1,"g":["shopping","price","display"],"p":["[표시가격]","[pʰjoɕiɡaɡjʌk]"],"f":1,"h":1},{"i":"d-sho-syo핑","k":"쇼핑","r":"syoping","t":{"w":"shopping","x":"'쇼핑' means 'shopping' in English.","e":["We say \"쇼핑\" in Korean.","In Korea, people often say \"쇼핑\".","\"쇼핑\" is an important expression in Korean.","Understanding the cultural context of \"쇼핑\" makes communication more natural."],"v":[["It is shopping.","There is shopping."],["It's shopping.","shopping, you know."],["shopping"]]},"p":["[쇼핑]","[syoping]"],"h":1},{"i":"d-sho-onrainsyo핑","k":"온라인쇼핑","r":"onlainsyoping","t":{"w":"online shopping","x":"'온라인쇼핑' means 'online shopping' in English.","e":["We say \"온라인쇼핑\" in Korean.","In Korea, people often say \"온라인쇼핑\".","\"온라인쇼핑\" is an important expression in Korean.","Understanding the cultural context of \"온라인쇼핑\" makes communication more natural."],"v":[["It is online shopping.","There is online shopping."],["It's online shopping.","online shopping, you know."],["online"]]},"p":["[온라인쇼핑]","[onlainsyoping]"],"h":1},{"i":"d-sho-opeurain","k":"오프라인","r":"opeurain","t":{"w":"offline","x":"'오프라인' means 'offline' in English.","e":["We say \"오프라인\" in Korean.","In Korea, people often say \"오프라인\".","\"오프라인\" is an important expression in Korean.","Understanding the cultural context of \"오프라인\" makes communication more natural."],"v":[["It is offline.","There is offline."],["It's offline.","offline, you know."],["offline"]]},"p":["[오프라인]","[opeurain]"],"h":1},{"i":"d-sho-결je","k":"결제","r":"gyeolje","t":{"w":"payment","x":"'결제' means 'payment' in English.","e":["We say \"결제\" in Korean.","In Korea, people often say \"결제\".","\"결제\" is an important expression in Korean.","Understanding the cultural context of \"결제\" makes communication more natural."],"v":[["It is payment.","There is payment."],["It's payment.","payment, you know."],["payment"]]},"p":["[결제]","[gyeolje]"],"h":1},{"i":"d-sho-sinyongkadeu","k":"신용카드","r":"sinyongkadeu","t":{"w":"credit card","x":"'신용카드' means 'credit card' in English.","e":["We say \"신용카드\" in Korean.","In Korea, people often say \"신용카드\".","\"신용카드\" is an important expression in Korean.","Understanding the cultural context of \"신용카드\" makes communication more natural."],"v":[["It is credit card.","There is credit card."],["It's credit card.","credit card, you know."],["credit"]]},"p":["[신용카드]","[sinyongkadeu]"],"h":1},{"i":"d-sho-chekeukadeu","k":"체크카드","r":"chekeukadeu","t":{"w":"debit card","x":"'체크카드' means 'debit card' in English.","e":["We say \"체크카드\" in Korean.","In Korea, people often say \"체크카드\".","\"체크카드\" is an important expression in Korean.","Understanding the cultural context of \"체크카드\" makes communication more natural."],"v":[["It is debit card.","There is debit card."],["It's debit card.","debit card, you know."],["debit"]]},"p":["[체크카드]","[chekeukadeu]"],"h":1},{"i":"d-sho-gyejwaiche","k":"계좌이체","r":"gyejwaiche","t":{"w":"bank transfer","x":"'계좌이체' means 'bank transfer' in English.","e":["We say \"계좌이체\" in Korean.","In Korea, people often say \"계좌이체\".","\"계좌이체\" is an important expression in Korean.","Understanding the cultural context of \"계좌이체\" makes communication more natural."],"v":[["It is bank transfer.","There is bank transfer."],["It's bank transfer.","bank transfer, you know."],["bank"]]},"p":["[계좌이체]","[gyejwaiche]"],"h":1},{"i":"d-sho-jeok립","k":"적립","r":"jeokrip","t":{"w":"accumulation","x":"'적립' means 'accumulation' in English.","e":["We say \"적립\" in Korean.","In Korea, people often say \"적립\".","\"적립\" is an important expression in Korean.","Understanding the cultural context of \"적립\" makes communication more natural."],"v":[["It is accumulation.","There is accumulation."],["It's accumulation.","accumulation, you know."],["accumulation"]]},"p":["[적립]","[jeokrip]"],"h":1},{"i":"d-sho-ban품","k":"반품","r":"banpum","t":{"w":"return","x":"'반품' means 'return' in English.","e":["We say \"반품\" in Korean.","In Korea, people often say \"반품\".","\"반품\" is an important expression in Korean.","Understanding the cultural context of \"반품\" makes communication more natural."],"v":[["It is return.","There is return."],["It's return.","return, you know."],["return"]]},"p":["[반품]","[banpum]"],"h":1},{"i":"d-sho-baesong","k":"배송","r":"baesong","t":{"w":"delivery","x":"'배송' means 'delivery' in English.","e":["We say \"배송\" in Korean.","In Korea, people often say \"배송\".","\"배송\" is an important expression in Korean.","Understanding the cultural context of \"배송\" makes communication more natural."],"v":[["It is delivery.","There is delivery."],["It's delivery.","delivery, you know."],["delivery"]]},"p":["[배송]","[baesong]"],"h":1},{"i":"d-sho-택bae","k":"택배","r":"taekbae","t":{"w":"courier","x":"'택배' means 'courier' in English.","e":["We say \"택배\" in Korean.","In Korea, people often say \"택배\".","\"택배\" is an important expression in Korean.","Understanding the cultural context of \"택배\" makes communication more natural."],"v":[["It is courier.","There is courier."],["It's courier.","courier, you know."],["courier"]]},"p":["[택배]","[taekbae]"],"h":1},{"i":"d-sho-muryobaesong","k":"무료배송","r":"muryobaesong","t":{"w":"free shipping","x":"'무료배송' means 'free shipping' in English.","e":["We say \"무료배송\" in Korean.","In Korea, people often say \"무료배송\".","\"무료배송\" is an important expression in Korean.","Understanding the cultural context of \"무료배송\" makes communication more natural."],"v":[["It is free shipping.","There is free shipping."],["It's free shipping.","free shipping, you know."],["free"]]},"p":["[무료배송]","[muryobaesong]"],"h":1},{"i":"d-sho-dangilbaesong","k":"당일배송","r":"dangilbaesong","t":{"w":"same-day delivery","x":"'당일배송' means 'same-day delivery' in English.","e":["We say \"당일배송\" in Korean.","In Korea, people often say \"당일배송\".","\"당일배송\" is an important expression in Korean.","Understanding the cultural context of \"당일배송\" makes communication more natural."],"v":[["It is same-day delivery.","There is same-day delivery."],["It's same-day delivery.","same-day delivery, you know."],["same-day"]]},"p":["[당일배송]","[dangilbaesong]"],"h":1},{"i":"d-sho-위siriseuteu","k":"위시리스트","r":"wisiriseuteu","t":{"w":"wishlist","x":"'위시리스트' means 'wishlist' in English.","e":["We say \"위시리스트\" in Korean.","In Korea, people often say \"위시리스트\".","\"위시리스트\" is an important expression in Korean.","Understanding the cultural context of \"위시리스트\" makes communication more natural."],"v":[["It is wishlist.","There is wishlist."],["It's wishlist.","wishlist, you know."],["wishlist"]]},"p":["[위시리스트]","[wisiriseuteu]"],"h":1},{"i":"d-sho-원ga","k":"원가","r":"wonga","t":{"w":"cost","x":"'원가' means 'cost' in English.","e":["We say \"원가\" in Korean.","In Korea, people often say \"원가\".","\"원가\" is an important expression in Korean.","Understanding the cultural context of \"원가\" makes communication more natural."],"v":[["It is cost.","There is cost."],["It's cost.","cost, you know."],["cost"]]},"p":["[원가]","[wonga]"],"h":1},{"i":"d-sho-halinga","k":"할인가","r":"halinga","t":{"w":"sale price","x":"'할인가' means 'sale price' in English.","e":["We say \"할인가\" in Korean.","In Korea, people often say \"할인가\".","\"할인가\" is an important expression in Korean.","Understanding the cultural context of \"할인가\" makes communication more natural."],"v":[["It is sale price.","There is sale price."],["It's sale price.","sale price, you know."],["sale"]]},"p":["[할인가]","[halinga]"],"h":1},{"i":"d-sho-bugase","k":"부가세","r":"bugase","t":{"w":"VAT","x":"'부가세' means 'VAT' in English.","e":["We say \"부가세\" in Korean.","In Korea, people often say \"부가세\".","\"부가세\" is an important expression in Korean.","Understanding the cultural context of \"부가세\" makes communication more natural."],"v":[["It is VAT.","There is VAT."],["It's VAT.","VAT, you know."],["VAT"]]},"p":["[부가세]","[bugase]"],"h":1},{"i":"d-sho-면se","k":"면세","r":"myeonse","t":{"w":"duty-free","x":"'면세' means 'duty-free' in English.","e":["We say \"면세\" in Korean.","In Korea, people often say \"면세\".","\"면세\" is an important expression in Korean.","Understanding the cultural context of \"면세\" makes communication more natural."],"v":[["It is duty-free.","There is duty-free."],["It's duty-free.","duty-free, you know."],["duty-free"]]},"p":["[면세]","[myeonse]"],"h":1}]}